{
  "단지정보": {
    "순번": 52,
    "단지ID": "140500",
    "단지명": "매매 2",
    "단지URL": "https://fin.land.naver.com/complexes/140500?tab=article&articleTradeTypes=A1",
    "수집시간": "2025-11-18T17:45:48.522424",
    "매물수": 3
  },
  "매물URL목록": [
    {
      "매물ID": "2556311723",
      "URL": "https://fin.land.naver.com/articles/2556311723",
      "매물정보": "매물 보러가기"
    },
    {
      "매물ID": "2557026551",
      "URL": "https://fin.land.naver.com/articles/2557026551",
      "매물정보": "매물 보러가기"
    },
    {
      "매물ID": "2557273033",
      "URL": "https://fin.land.naver.com/articles/2557273033",
      "매물정보": "매물 보러가기"
    }
  ]
}