{
  "단지정보": {
    "순번": 10,
    "단지ID": "9716",
    "단지명": "아파트354세대2004. 5.(22년차)",
    "단지URL": "https://fin.land.naver.com/complexes/9716?tab=article&articleTradeTypes=A1",
    "수집시간": "2025-11-18T18:31:05.070017",
    "매물수": 37
  },
  "매물URL목록": [
    {
      "매물ID": "2562026759",
      "URL": "https://fin.land.naver.com/articles/2562026759",
      "매물정보": "매물 보러가기"
    },
    {
      "매물ID": "2561972018",
      "URL": "https://fin.land.naver.com/articles/2561972018",
      "매물정보": "매물 보러가기"
    },
    {
      "매물ID": "2562010970",
      "URL": "https://fin.land.naver.com/articles/2562010970",
      "매물정보": "매물 보러가기"
    },
    {
      "매물ID": "2561311064",
      "URL": "https://fin.land.naver.com/articles/2561311064",
      "매물정보": "매물 보러가기"
    },
    {
      "매물ID": "2559267629",
      "URL": "https://fin.land.naver.com/articles/2559267629",
      "매물정보": "매물 보러가기"
    },
    {
      "매물ID": "2558814537",
      "URL": "https://fin.land.naver.com/articles/2558814537",
      "매물정보": "매물 보러가기"
    },
    {
      "매물ID": "2560590456",
      "URL": "https://fin.land.naver.com/articles/2560590456",
      "매물정보": "매물 보러가기"
    },
    {
      "매물ID": "2557568290",
      "URL": "https://fin.land.naver.com/articles/2557568290",
      "매물정보": "매물 보러가기"
    },
    {
      "매물ID": "2561924883",
      "URL": "https://fin.land.naver.com/articles/2561924883",
      "매물정보": "매물 보러가기"
    },
    {
      "매물ID": "2561373880",
      "URL": "https://fin.land.naver.com/articles/2561373880",
      "매물정보": "매물 보러가기"
    },
    {
      "매물ID": "2559935044",
      "URL": "https://fin.land.naver.com/articles/2559935044",
      "매물정보": "매물 보러가기"
    },
    {
      "매물ID": "2560455476",
      "URL": "https://fin.land.naver.com/articles/2560455476",
      "매물정보": "매물 보러가기"
    },
    {
      "매물ID": "2557462366",
      "URL": "https://fin.land.naver.com/articles/2557462366",
      "매물정보": "매물 보러가기"
    },
    {
      "매물ID": "2558496426",
      "URL": "https://fin.land.naver.com/articles/2558496426",
      "매물정보": "매물 보러가기"
    },
    {
      "매물ID": "2556311497",
      "URL": "https://fin.land.naver.com/articles/2556311497",
      "매물정보": "매물 보러가기"
    },
    {
      "매물ID": "2556476548",
      "URL": "https://fin.land.naver.com/articles/2556476548",
      "매물정보": "매물 보러가기"
    },
    {
      "매물ID": "2557186100",
      "URL": "https://fin.land.naver.com/articles/2557186100",
      "매물정보": "매물 보러가기"
    },
    {
      "매물ID": "2556215715",
      "URL": "https://fin.land.naver.com/articles/2556215715",
      "매물정보": "매물 보러가기"
    },
    {
      "매물ID": "2556309091",
      "URL": "https://fin.land.naver.com/articles/2556309091",
      "매물정보": "매물 보러가기"
    },
    {
      "매물ID": "2557172240",
      "URL": "https://fin.land.naver.com/articles/2557172240",
      "매물정보": "매물 보러가기"
    },
    {
      "매물ID": "2561738073",
      "URL": "https://fin.land.naver.com/articles/2561738073",
      "매물정보": "매물 보러가기"
    },
    {
      "매물ID": "2560185636",
      "URL": "https://fin.land.naver.com/articles/2560185636",
      "매물정보": "매물 보러가기"
    },
    {
      "매물ID": "2561101853",
      "URL": "https://fin.land.naver.com/articles/2561101853",
      "매물정보": "매물 보러가기"
    },
    {
      "매물ID": "2559715956",
      "URL": "https://fin.land.naver.com/articles/2559715956",
      "매물정보": "매물 보러가기"
    },
    {
      "매물ID": "2559001552",
      "URL": "https://fin.land.naver.com/articles/2559001552",
      "매물정보": "매물 보러가기"
    },
    {
      "매물ID": "2560585676",
      "URL": "https://fin.land.naver.com/articles/2560585676",
      "매물정보": "매물 보러가기"
    },
    {
      "매물ID": "2560568471",
      "URL": "https://fin.land.naver.com/articles/2560568471",
      "매물정보": "매물 보러가기"
    },
    {
      "매물ID": "2560386013",
      "URL": "https://fin.land.naver.com/articles/2560386013",
      "매물정보": "매물 보러가기"
    },
    {
      "매물ID": "2559721491",
      "URL": "https://fin.land.naver.com/articles/2559721491",
      "매물정보": "매물 보러가기"
    },
    {
      "매물ID": "2561227640",
      "URL": "https://fin.land.naver.com/articles/2561227640",
      "매물정보": "매물 보러가기"
    },
    {
      "매물ID": "2560001350",
      "URL": "https://fin.land.naver.com/articles/2560001350",
      "매물정보": "매물 보러가기"
    },
    {
      "매물ID": "2560376997",
      "URL": "https://fin.land.naver.com/articles/2560376997",
      "매물정보": "매물 보러가기"
    },
    {
      "매물ID": "2558741880",
      "URL": "https://fin.land.naver.com/articles/2558741880",
      "매물정보": "매물 보러가기"
    },
    {
      "매물ID": "2556954392",
      "URL": "https://fin.land.naver.com/articles/2556954392",
      "매물정보": "매물 보러가기"
    },
    {
      "매물ID": "2557330481",
      "URL": "https://fin.land.naver.com/articles/2557330481",
      "매물정보": "매물 보러가기"
    },
    {
      "매물ID": "2558717506",
      "URL": "https://fin.land.naver.com/articles/2558717506",
      "매물정보": "매물 보러가기"
    },
    {
      "매물ID": "2556459624",
      "URL": "https://fin.land.naver.com/articles/2556459624",
      "매물정보": "매물 보러가기"
    }
  ]
}