{
  "단지정보": {
    "순번": 76,
    "단지ID": "104016",
    "단지명": "아파트14세대2000. 9.(26년차)",
    "단지URL": "https://fin.land.naver.com/complexes/104016?tab=article&articleTradeTypes=A1",
    "수집시간": "2025-11-19T21:11:24.039282",
    "매물수": 5
  },
  "매물URL목록": [
    {
      "매물ID": "2558418305",
      "URL": "https://fin.land.naver.com/articles/2558418305",
      "매물정보": "매물 보러가기"
    },
    {
      "매물ID": "2557604188",
      "URL": "https://fin.land.naver.com/articles/2557604188",
      "매물정보": "매물 보러가기"
    },
    {
      "매물ID": "2557774445",
      "URL": "https://fin.land.naver.com/articles/2557774445",
      "매물정보": "매물 보러가기"
    },
    {
      "매물ID": "2558119782",
      "URL": "https://fin.land.naver.com/articles/2558119782",
      "매물정보": "매물 보러가기"
    },
    {
      "매물ID": "2558120168",
      "URL": "https://fin.land.naver.com/articles/2558120168",
      "매물정보": "매물 보러가기"
    }
  ]
}