{
  "단지정보": {
    "순번": 37,
    "단지ID": "19019",
    "단지명": "매매 8",
    "단지URL": "https://fin.land.naver.com/complexes/19019?tab=article&articleTradeTypes=A1",
    "수집시간": "2025-11-19T19:54:55.633879",
    "매물수": 60
  },
  "매물URL목록": [
    {
      "매물ID": "2562334431",
      "URL": "https://fin.land.naver.com/articles/2562334431",
      "매물정보": "매물 보러가기"
    },
    {
      "매물ID": "2562287543",
      "URL": "https://fin.land.naver.com/articles/2562287543",
      "매물정보": "매물 보러가기"
    },
    {
      "매물ID": "2561707371",
      "URL": "https://fin.land.naver.com/articles/2561707371",
      "매물정보": "매물 보러가기"
    },
    {
      "매물ID": "2561206742",
      "URL": "https://fin.land.naver.com/articles/2561206742",
      "매물정보": "매물 보러가기"
    },
    {
      "매물ID": "2558920662",
      "URL": "https://fin.land.naver.com/articles/2558920662",
      "매물정보": "매물 보러가기"
    },
    {
      "매물ID": "2561406043",
      "URL": "https://fin.land.naver.com/articles/2561406043",
      "매물정보": "매물 보러가기"
    },
    {
      "매물ID": "2561381446",
      "URL": "https://fin.land.naver.com/articles/2561381446",
      "매물정보": "매물 보러가기"
    },
    {
      "매물ID": "2561385742",
      "URL": "https://fin.land.naver.com/articles/2561385742",
      "매물정보": "매물 보러가기"
    },
    {
      "매물ID": "2560919575",
      "URL": "https://fin.land.naver.com/articles/2560919575",
      "매물정보": "매물 보러가기"
    },
    {
      "매물ID": "2560500055",
      "URL": "https://fin.land.naver.com/articles/2560500055",
      "매물정보": "매물 보러가기"
    },
    {
      "매물ID": "2562138279",
      "URL": "https://fin.land.naver.com/articles/2562138279",
      "매물정보": "매물 보러가기"
    },
    {
      "매물ID": "2559635595",
      "URL": "https://fin.land.naver.com/articles/2559635595",
      "매물정보": "매물 보러가기"
    },
    {
      "매물ID": "2556641197",
      "URL": "https://fin.land.naver.com/articles/2556641197",
      "매물정보": "매물 보러가기"
    },
    {
      "매물ID": "2561923341",
      "URL": "https://fin.land.naver.com/articles/2561923341",
      "매물정보": "매물 보러가기"
    },
    {
      "매물ID": "2562220570",
      "URL": "https://fin.land.naver.com/articles/2562220570",
      "매물정보": "매물 보러가기"
    },
    {
      "매물ID": "2556582164",
      "URL": "https://fin.land.naver.com/articles/2556582164",
      "매물정보": "매물 보러가기"
    },
    {
      "매물ID": "2562169552",
      "URL": "https://fin.land.naver.com/articles/2562169552",
      "매물정보": "매물 보러가기"
    },
    {
      "매물ID": "2560628340",
      "URL": "https://fin.land.naver.com/articles/2560628340",
      "매물정보": "매물 보러가기"
    },
    {
      "매물ID": "2562339725",
      "URL": "https://fin.land.naver.com/articles/2562339725",
      "매물정보": "매물 보러가기"
    },
    {
      "매물ID": "2561593602",
      "URL": "https://fin.land.naver.com/articles/2561593602",
      "매물정보": "매물 보러가기"
    },
    {
      "매물ID": "2561624172",
      "URL": "https://fin.land.naver.com/articles/2561624172",
      "매물정보": "매물 보러가기"
    },
    {
      "매물ID": "2558062480",
      "URL": "https://fin.land.naver.com/articles/2558062480",
      "매물정보": "매물 보러가기"
    },
    {
      "매물ID": "2556926051",
      "URL": "https://fin.land.naver.com/articles/2556926051",
      "매물정보": "네이버페이 부동산에서 보기"
    },
    {
      "매물ID": "2561923187",
      "URL": "https://fin.land.naver.com/articles/2561923187",
      "매물정보": "매물 보러가기"
    },
    {
      "매물ID": "2561371320",
      "URL": "https://fin.land.naver.com/articles/2561371320",
      "매물정보": "매물 보러가기"
    },
    {
      "매물ID": "2559572953",
      "URL": "https://fin.land.naver.com/articles/2559572953",
      "매물정보": "매물 보러가기"
    },
    {
      "매물ID": "2561385527",
      "URL": "https://fin.land.naver.com/articles/2561385527",
      "매물정보": "매물 보러가기"
    },
    {
      "매물ID": "2561324469",
      "URL": "https://fin.land.naver.com/articles/2561324469",
      "매물정보": "매물 보러가기"
    },
    {
      "매물ID": "2561538495",
      "URL": "https://fin.land.naver.com/articles/2561538495",
      "매물정보": "매물 보러가기"
    },
    {
      "매물ID": "2561084162",
      "URL": "https://fin.land.naver.com/articles/2561084162",
      "매물정보": "매물 보러가기"
    },
    {
      "매물ID": "2561035068",
      "URL": "https://fin.land.naver.com/articles/2561035068",
      "매물정보": "네이버페이 부동산에서 보기"
    },
    {
      "매물ID": "2561923022",
      "URL": "https://fin.land.naver.com/articles/2561923022",
      "매물정보": "매물 보러가기"
    },
    {
      "매물ID": "2562258978",
      "URL": "https://fin.land.naver.com/articles/2562258978",
      "매물정보": "매물 보러가기"
    },
    {
      "매물ID": "2562142521",
      "URL": "https://fin.land.naver.com/articles/2562142521",
      "매물정보": "매물 보러가기"
    },
    {
      "매물ID": "2561834720",
      "URL": "https://fin.land.naver.com/articles/2561834720",
      "매물정보": "매물 보러가기"
    },
    {
      "매물ID": "2561764320",
      "URL": "https://fin.land.naver.com/articles/2561764320",
      "매물정보": "매물 보러가기"
    },
    {
      "매물ID": "2561612360",
      "URL": "https://fin.land.naver.com/articles/2561612360",
      "매물정보": "매물 보러가기"
    },
    {
      "매물ID": "2561529096",
      "URL": "https://fin.land.naver.com/articles/2561529096",
      "매물정보": "매물 보러가기"
    },
    {
      "매물ID": "2559575680",
      "URL": "https://fin.land.naver.com/articles/2559575680",
      "매물정보": "매물 보러가기"
    },
    {
      "매물ID": "2558827517",
      "URL": "https://fin.land.naver.com/articles/2558827517",
      "매물정보": "매물 보러가기"
    },
    {
      "매물ID": "2557558815",
      "URL": "https://fin.land.naver.com/articles/2557558815",
      "매물정보": "매물 보러가기"
    },
    {
      "매물ID": "2560463766",
      "URL": "https://fin.land.naver.com/articles/2560463766",
      "매물정보": "매물 보러가기"
    },
    {
      "매물ID": "2558917760",
      "URL": "https://fin.land.naver.com/articles/2558917760",
      "매물정보": "매물 보러가기"
    },
    {
      "매물ID": "2560388565",
      "URL": "https://fin.land.naver.com/articles/2560388565",
      "매물정보": "매물 보러가기"
    },
    {
      "매물ID": "2556829421",
      "URL": "https://fin.land.naver.com/articles/2556829421",
      "매물정보": "매물 보러가기"
    },
    {
      "매물ID": "2556342731",
      "URL": "https://fin.land.naver.com/articles/2556342731",
      "매물정보": "매물 보러가기"
    },
    {
      "매물ID": "2558915748",
      "URL": "https://fin.land.naver.com/articles/2558915748",
      "매물정보": "매물 보러가기"
    },
    {
      "매물ID": "2558720024",
      "URL": "https://fin.land.naver.com/articles/2558720024",
      "매물정보": "매물 보러가기"
    },
    {
      "매물ID": "2557742709",
      "URL": "https://fin.land.naver.com/articles/2557742709",
      "매물정보": "매물 보러가기"
    },
    {
      "매물ID": "2559900356",
      "URL": "https://fin.land.naver.com/articles/2559900356",
      "매물정보": "매물 보러가기"
    },
    {
      "매물ID": "2556345926",
      "URL": "https://fin.land.naver.com/articles/2556345926",
      "매물정보": "매물 보러가기"
    },
    {
      "매물ID": "2559604967",
      "URL": "https://fin.land.naver.com/articles/2559604967",
      "매물정보": "매물 보러가기"
    },
    {
      "매물ID": "2559143328",
      "URL": "https://fin.land.naver.com/articles/2559143328",
      "매물정보": "매물 보러가기"
    },
    {
      "매물ID": "2558624195",
      "URL": "https://fin.land.naver.com/articles/2558624195",
      "매물정보": "매물 보러가기"
    },
    {
      "매물ID": "2558252758",
      "URL": "https://fin.land.naver.com/articles/2558252758",
      "매물정보": "매물 보러가기"
    },
    {
      "매물ID": "2556712281",
      "URL": "https://fin.land.naver.com/articles/2556712281",
      "매물정보": "매물 보러가기"
    },
    {
      "매물ID": "2561840922",
      "URL": "https://fin.land.naver.com/articles/2561840922",
      "매물정보": "매물 보러가기"
    },
    {
      "매물ID": "2561838841",
      "URL": "https://fin.land.naver.com/articles/2561838841",
      "매물정보": "매물 보러가기"
    },
    {
      "매물ID": "2559772639",
      "URL": "https://fin.land.naver.com/articles/2559772639",
      "매물정보": "매물 보러가기"
    },
    {
      "매물ID": "2557202561",
      "URL": "https://fin.land.naver.com/articles/2557202561",
      "매물정보": "매물 보러가기"
    }
  ]
}