{
  "단지정보": {
    "순번": 39,
    "단지ID": "110893",
    "단지명": "매매 23",
    "단지URL": "https://fin.land.naver.com/complexes/110893?tab=article&articleTradeTypes=A1",
    "수집시간": "2025-11-18T02:45:42.466015",
    "매물수": 84
  },
  "매물URL목록": [
    {
      "매물ID": "2561819996",
      "URL": "https://fin.land.naver.com/articles/2561819996",
      "매물정보": "매물 보러가기"
    },
    {
      "매물ID": "2560485520",
      "URL": "https://fin.land.naver.com/articles/2560485520",
      "매물정보": "매물 보러가기"
    },
    {
      "매물ID": "2560636212",
      "URL": "https://fin.land.naver.com/articles/2560636212",
      "매물정보": "매물 보러가기"
    },
    {
      "매물ID": "2560437342",
      "URL": "https://fin.land.naver.com/articles/2560437342",
      "매물정보": "매물 보러가기"
    },
    {
      "매물ID": "2560448022",
      "URL": "https://fin.land.naver.com/articles/2560448022",
      "매물정보": "매물 보러가기"
    },
    {
      "매물ID": "2561906886",
      "URL": "https://fin.land.naver.com/articles/2561906886",
      "매물정보": "매물 보러가기"
    },
    {
      "매물ID": "2561858109",
      "URL": "https://fin.land.naver.com/articles/2561858109",
      "매물정보": "매물 보러가기"
    },
    {
      "매물ID": "2558900983",
      "URL": "https://fin.land.naver.com/articles/2558900983",
      "매물정보": "매물 보러가기"
    },
    {
      "매물ID": "2558545824",
      "URL": "https://fin.land.naver.com/articles/2558545824",
      "매물정보": "매물 보러가기"
    },
    {
      "매물ID": "2558690555",
      "URL": "https://fin.land.naver.com/articles/2558690555",
      "매물정보": "매물 보러가기"
    },
    {
      "매물ID": "2558662909",
      "URL": "https://fin.land.naver.com/articles/2558662909",
      "매물정보": "매물 보러가기"
    },
    {
      "매물ID": "2558746741",
      "URL": "https://fin.land.naver.com/articles/2558746741",
      "매물정보": "매물 보러가기"
    },
    {
      "매물ID": "2559760465",
      "URL": "https://fin.land.naver.com/articles/2559760465",
      "매물정보": "매물 보러가기"
    },
    {
      "매물ID": "2558307097",
      "URL": "https://fin.land.naver.com/articles/2558307097",
      "매물정보": "매물 보러가기"
    },
    {
      "매물ID": "2558509598",
      "URL": "https://fin.land.naver.com/articles/2558509598",
      "매물정보": "매물 보러가기"
    },
    {
      "매물ID": "2558245881",
      "URL": "https://fin.land.naver.com/articles/2558245881",
      "매물정보": "매물 보러가기"
    },
    {
      "매물ID": "2559175145",
      "URL": "https://fin.land.naver.com/articles/2559175145",
      "매물정보": "매물 보러가기"
    },
    {
      "매물ID": "2560823718",
      "URL": "https://fin.land.naver.com/articles/2560823718",
      "매물정보": "매물 보러가기"
    },
    {
      "매물ID": "2558706874",
      "URL": "https://fin.land.naver.com/articles/2558706874",
      "매물정보": "매물 보러가기"
    },
    {
      "매물ID": "2558344561",
      "URL": "https://fin.land.naver.com/articles/2558344561",
      "매물정보": "매물 보러가기"
    },
    {
      "매물ID": "2557385333",
      "URL": "https://fin.land.naver.com/articles/2557385333",
      "매물정보": "매물 보러가기"
    },
    {
      "매물ID": "2557375343",
      "URL": "https://fin.land.naver.com/articles/2557375343",
      "매물정보": "매물 보러가기"
    },
    {
      "매물ID": "2556553684",
      "URL": "https://fin.land.naver.com/articles/2556553684",
      "매물정보": "매물 보러가기"
    },
    {
      "매물ID": "2558714105",
      "URL": "https://fin.land.naver.com/articles/2558714105",
      "매물정보": "매물 보러가기"
    },
    {
      "매물ID": "2559449136",
      "URL": "https://fin.land.naver.com/articles/2559449136",
      "매물정보": "매물 보러가기"
    },
    {
      "매물ID": "2558497719",
      "URL": "https://fin.land.naver.com/articles/2558497719",
      "매물정보": "매물 보러가기"
    },
    {
      "매물ID": "2557381266",
      "URL": "https://fin.land.naver.com/articles/2557381266",
      "매물정보": "매물 보러가기"
    },
    {
      "매물ID": "2561374893",
      "URL": "https://fin.land.naver.com/articles/2561374893",
      "매물정보": "매물 보러가기"
    },
    {
      "매물ID": "2561053580",
      "URL": "https://fin.land.naver.com/articles/2561053580",
      "매물정보": "매물 보러가기"
    },
    {
      "매물ID": "2559638602",
      "URL": "https://fin.land.naver.com/articles/2559638602",
      "매물정보": "매물 보러가기"
    },
    {
      "매물ID": "2558314433",
      "URL": "https://fin.land.naver.com/articles/2558314433",
      "매물정보": "매물 보러가기"
    },
    {
      "매물ID": "2560888491",
      "URL": "https://fin.land.naver.com/articles/2560888491",
      "매물정보": "매물 보러가기"
    },
    {
      "매물ID": "2561039166",
      "URL": "https://fin.land.naver.com/articles/2561039166",
      "매물정보": "매물 보러가기"
    },
    {
      "매물ID": "2561747815",
      "URL": "https://fin.land.naver.com/articles/2561747815",
      "매물정보": "매물 보러가기"
    },
    {
      "매물ID": "2560084317",
      "URL": "https://fin.land.naver.com/articles/2560084317",
      "매물정보": "매물 보러가기"
    },
    {
      "매물ID": "2561784621",
      "URL": "https://fin.land.naver.com/articles/2561784621",
      "매물정보": "매물 보러가기"
    },
    {
      "매물ID": "2559246664",
      "URL": "https://fin.land.naver.com/articles/2559246664",
      "매물정보": "매물 보러가기"
    },
    {
      "매물ID": "2561386643",
      "URL": "https://fin.land.naver.com/articles/2561386643",
      "매물정보": "매물 보러가기"
    },
    {
      "매물ID": "2556256502",
      "URL": "https://fin.land.naver.com/articles/2556256502",
      "매물정보": "매물 보러가기"
    },
    {
      "매물ID": "2561153648",
      "URL": "https://fin.land.naver.com/articles/2561153648",
      "매물정보": "매물 보러가기"
    },
    {
      "매물ID": "2560785827",
      "URL": "https://fin.land.naver.com/articles/2560785827",
      "매물정보": "매물 보러가기"
    },
    {
      "매물ID": "2560883131",
      "URL": "https://fin.land.naver.com/articles/2560883131",
      "매물정보": "매물 보러가기"
    },
    {
      "매물ID": "2557860580",
      "URL": "https://fin.land.naver.com/articles/2557860580",
      "매물정보": "매물 보러가기"
    },
    {
      "매물ID": "2560396920",
      "URL": "https://fin.land.naver.com/articles/2560396920",
      "매물정보": "매물 보러가기"
    },
    {
      "매물ID": "2560627389",
      "URL": "https://fin.land.naver.com/articles/2560627389",
      "매물정보": "매물 보러가기"
    },
    {
      "매물ID": "2559899996",
      "URL": "https://fin.land.naver.com/articles/2559899996",
      "매물정보": "매물 보러가기"
    },
    {
      "매물ID": "2559778687",
      "URL": "https://fin.land.naver.com/articles/2559778687",
      "매물정보": "매물 보러가기"
    },
    {
      "매물ID": "2560849917",
      "URL": "https://fin.land.naver.com/articles/2560849917",
      "매물정보": "매물 보러가기"
    },
    {
      "매물ID": "2559360375",
      "URL": "https://fin.land.naver.com/articles/2559360375",
      "매물정보": "매물 보러가기"
    },
    {
      "매물ID": "2556339313",
      "URL": "https://fin.land.naver.com/articles/2556339313",
      "매물정보": "매물 보러가기"
    },
    {
      "매물ID": "2560000278",
      "URL": "https://fin.land.naver.com/articles/2560000278",
      "매물정보": "매물 보러가기"
    },
    {
      "매물ID": "2561891931",
      "URL": "https://fin.land.naver.com/articles/2561891931",
      "매물정보": "매물 보러가기"
    },
    {
      "매물ID": "2561888131",
      "URL": "https://fin.land.naver.com/articles/2561888131",
      "매물정보": "매물 보러가기"
    },
    {
      "매물ID": "2561862770",
      "URL": "https://fin.land.naver.com/articles/2561862770",
      "매물정보": "매물 보러가기"
    },
    {
      "매물ID": "2561750237",
      "URL": "https://fin.land.naver.com/articles/2561750237",
      "매물정보": "매물 보러가기"
    },
    {
      "매물ID": "2559679819",
      "URL": "https://fin.land.naver.com/articles/2559679819",
      "매물정보": "매물 보러가기"
    },
    {
      "매물ID": "2558640748",
      "URL": "https://fin.land.naver.com/articles/2558640748",
      "매물정보": "매물 보러가기"
    },
    {
      "매물ID": "2558061254",
      "URL": "https://fin.land.naver.com/articles/2558061254",
      "매물정보": "매물 보러가기"
    },
    {
      "매물ID": "2559341162",
      "URL": "https://fin.land.naver.com/articles/2559341162",
      "매물정보": "매물 보러가기"
    },
    {
      "매물ID": "2557766213",
      "URL": "https://fin.land.naver.com/articles/2557766213",
      "매물정보": "매물 보러가기"
    },
    {
      "매물ID": "2559600604",
      "URL": "https://fin.land.naver.com/articles/2559600604",
      "매물정보": "매물 보러가기"
    },
    {
      "매물ID": "2560661070",
      "URL": "https://fin.land.naver.com/articles/2560661070",
      "매물정보": "매물 보러가기"
    },
    {
      "매물ID": "2557503480",
      "URL": "https://fin.land.naver.com/articles/2557503480",
      "매물정보": "매물 보러가기"
    },
    {
      "매물ID": "2559231750",
      "URL": "https://fin.land.naver.com/articles/2559231750",
      "매물정보": "매물 보러가기"
    },
    {
      "매물ID": "2558343526",
      "URL": "https://fin.land.naver.com/articles/2558343526",
      "매물정보": "매물 보러가기"
    },
    {
      "매물ID": "2558326601",
      "URL": "https://fin.land.naver.com/articles/2558326601",
      "매물정보": "매물 보러가기"
    },
    {
      "매물ID": "2560027211",
      "URL": "https://fin.land.naver.com/articles/2560027211",
      "매물정보": "매물 보러가기"
    },
    {
      "매물ID": "2558214507",
      "URL": "https://fin.land.naver.com/articles/2558214507",
      "매물정보": "매물 보러가기"
    },
    {
      "매물ID": "2558010740",
      "URL": "https://fin.land.naver.com/articles/2558010740",
      "매물정보": "매물 보러가기"
    },
    {
      "매물ID": "2558010412",
      "URL": "https://fin.land.naver.com/articles/2558010412",
      "매물정보": "매물 보러가기"
    },
    {
      "매물ID": "2558010345",
      "URL": "https://fin.land.naver.com/articles/2558010345",
      "매물정보": "매물 보러가기"
    },
    {
      "매물ID": "2557996086",
      "URL": "https://fin.land.naver.com/articles/2557996086",
      "매물정보": "매물 보러가기"
    },
    {
      "매물ID": "2557995307",
      "URL": "https://fin.land.naver.com/articles/2557995307",
      "매물정보": "매물 보러가기"
    },
    {
      "매물ID": "2557994911",
      "URL": "https://fin.land.naver.com/articles/2557994911",
      "매물정보": "매물 보러가기"
    },
    {
      "매물ID": "2559836450",
      "URL": "https://fin.land.naver.com/articles/2559836450",
      "매물정보": "매물 보러가기"
    },
    {
      "매물ID": "2558294325",
      "URL": "https://fin.land.naver.com/articles/2558294325",
      "매물정보": "매물 보러가기"
    },
    {
      "매물ID": "2557635905",
      "URL": "https://fin.land.naver.com/articles/2557635905",
      "매물정보": "매물 보러가기"
    },
    {
      "매물ID": "2558499183",
      "URL": "https://fin.land.naver.com/articles/2558499183",
      "매물정보": "매물 보러가기"
    },
    {
      "매물ID": "2557636588",
      "URL": "https://fin.land.naver.com/articles/2557636588",
      "매물정보": "매물 보러가기"
    },
    {
      "매물ID": "2557064626",
      "URL": "https://fin.land.naver.com/articles/2557064626",
      "매물정보": "매물 보러가기"
    },
    {
      "매물ID": "2556911807",
      "URL": "https://fin.land.naver.com/articles/2556911807",
      "매물정보": "매물 보러가기"
    },
    {
      "매물ID": "2561429862",
      "URL": "https://fin.land.naver.com/articles/2561429862",
      "매물정보": "매물 보러가기"
    },
    {
      "매물ID": "2561363852",
      "URL": "https://fin.land.naver.com/articles/2561363852",
      "매물정보": "매물 보러가기"
    },
    {
      "매물ID": "2561032409",
      "URL": "https://fin.land.naver.com/articles/2561032409",
      "매물정보": "매물 보러가기"
    }
  ]
}