{
  "단지정보": {
    "순번": 19,
    "단지ID": "1014",
    "단지명": "아파트164세대1999. 4.(27년차)",
    "단지URL": "https://fin.land.naver.com/complexes/1014?tab=article&articleTradeTypes=A1",
    "수집시간": "2025-11-18T17:37:46.226983",
    "매물수": 22
  },
  "매물URL목록": [
    {
      "매물ID": "2560144819",
      "URL": "https://fin.land.naver.com/articles/2560144819",
      "매물정보": "매물 보러가기"
    },
    {
      "매물ID": "2560150044",
      "URL": "https://fin.land.naver.com/articles/2560150044",
      "매물정보": "매물 보러가기"
    },
    {
      "매물ID": "2559503193",
      "URL": "https://fin.land.naver.com/articles/2559503193",
      "매물정보": "매물 보러가기"
    },
    {
      "매물ID": "2559075057",
      "URL": "https://fin.land.naver.com/articles/2559075057",
      "매물정보": "매물 보러가기"
    },
    {
      "매물ID": "2558412818",
      "URL": "https://fin.land.naver.com/articles/2558412818",
      "매물정보": "매물 보러가기"
    },
    {
      "매물ID": "2558186437",
      "URL": "https://fin.land.naver.com/articles/2558186437",
      "매물정보": "매물 보러가기"
    },
    {
      "매물ID": "2561069725",
      "URL": "https://fin.land.naver.com/articles/2561069725",
      "매물정보": "매물 보러가기"
    },
    {
      "매물ID": "2558737556",
      "URL": "https://fin.land.naver.com/articles/2558737556",
      "매물정보": "매물 보러가기"
    },
    {
      "매물ID": "2561069019",
      "URL": "https://fin.land.naver.com/articles/2561069019",
      "매물정보": "매물 보러가기"
    },
    {
      "매물ID": "2556441984",
      "URL": "https://fin.land.naver.com/articles/2556441984",
      "매물정보": "매물 보러가기"
    },
    {
      "매물ID": "2560241061",
      "URL": "https://fin.land.naver.com/articles/2560241061",
      "매물정보": "매물 보러가기"
    },
    {
      "매물ID": "2559961360",
      "URL": "https://fin.land.naver.com/articles/2559961360",
      "매물정보": "매물 보러가기"
    },
    {
      "매물ID": "2560404576",
      "URL": "https://fin.land.naver.com/articles/2560404576",
      "매물정보": "매물 보러가기"
    },
    {
      "매물ID": "2559140160",
      "URL": "https://fin.land.naver.com/articles/2559140160",
      "매물정보": "매물 보러가기"
    },
    {
      "매물ID": "2558411913",
      "URL": "https://fin.land.naver.com/articles/2558411913",
      "매물정보": "매물 보러가기"
    },
    {
      "매물ID": "2557673250",
      "URL": "https://fin.land.naver.com/articles/2557673250",
      "매물정보": "매물 보러가기"
    },
    {
      "매물ID": "2557544095",
      "URL": "https://fin.land.naver.com/articles/2557544095",
      "매물정보": "매물 보러가기"
    },
    {
      "매물ID": "2558467667",
      "URL": "https://fin.land.naver.com/articles/2558467667",
      "매물정보": "매물 보러가기"
    },
    {
      "매물ID": "2558210400",
      "URL": "https://fin.land.naver.com/articles/2558210400",
      "매물정보": "매물 보러가기"
    },
    {
      "매물ID": "2557996482",
      "URL": "https://fin.land.naver.com/articles/2557996482",
      "매물정보": "매물 보러가기"
    },
    {
      "매물ID": "2556491901",
      "URL": "https://fin.land.naver.com/articles/2556491901",
      "매물정보": "매물 보러가기"
    },
    {
      "매물ID": "2559657853",
      "URL": "https://fin.land.naver.com/articles/2559657853",
      "매물정보": "매물 보러가기"
    }
  ]
}