{
  "단지정보": {
    "순번": 29,
    "단지ID": "1018",
    "단지명": "아파트221세대1995. 9.(31년차)",
    "단지URL": "https://fin.land.naver.com/complexes/1018?tab=article&articleTradeTypes=A1",
    "수집시간": "2025-11-18T14:36:16.835057",
    "매물수": 28
  },
  "매물URL목록": [
    {
      "매물ID": "2561980334",
      "URL": "https://fin.land.naver.com/articles/2561980334",
      "매물정보": "매물 보러가기"
    },
    {
      "매물ID": "2561902942",
      "URL": "https://fin.land.naver.com/articles/2561902942",
      "매물정보": "매물 보러가기"
    },
    {
      "매물ID": "2561691791",
      "URL": "https://fin.land.naver.com/articles/2561691791",
      "매물정보": "매물 보러가기"
    },
    {
      "매물ID": "2560982618",
      "URL": "https://fin.land.naver.com/articles/2560982618",
      "매물정보": "매물 보러가기"
    },
    {
      "매물ID": "2560387156",
      "URL": "https://fin.land.naver.com/articles/2560387156",
      "매물정보": "매물 보러가기"
    },
    {
      "매물ID": "2560139181",
      "URL": "https://fin.land.naver.com/articles/2560139181",
      "매물정보": "매물 보러가기"
    },
    {
      "매물ID": "2559228229",
      "URL": "https://fin.land.naver.com/articles/2559228229",
      "매물정보": "네이버페이 부동산에서 보기"
    },
    {
      "매물ID": "2560972265",
      "URL": "https://fin.land.naver.com/articles/2560972265",
      "매물정보": "매물 보러가기"
    },
    {
      "매물ID": "2560532392",
      "URL": "https://fin.land.naver.com/articles/2560532392",
      "매물정보": "매물 보러가기"
    },
    {
      "매물ID": "2558223423",
      "URL": "https://fin.land.naver.com/articles/2558223423",
      "매물정보": "매물 보러가기"
    },
    {
      "매물ID": "2558436679",
      "URL": "https://fin.land.naver.com/articles/2558436679",
      "매물정보": "매물 보러가기"
    },
    {
      "매물ID": "2558662500",
      "URL": "https://fin.land.naver.com/articles/2558662500",
      "매물정보": "매물 보러가기"
    },
    {
      "매물ID": "2561881233",
      "URL": "https://fin.land.naver.com/articles/2561881233",
      "매물정보": "매물 보러가기"
    },
    {
      "매물ID": "2558033486",
      "URL": "https://fin.land.naver.com/articles/2558033486",
      "매물정보": "매물 보러가기"
    },
    {
      "매물ID": "2561647812",
      "URL": "https://fin.land.naver.com/articles/2561647812",
      "매물정보": "매물 보러가기"
    },
    {
      "매물ID": "2560307428",
      "URL": "https://fin.land.naver.com/articles/2560307428",
      "매물정보": "매물 보러가기"
    },
    {
      "매물ID": "2557511722",
      "URL": "https://fin.land.naver.com/articles/2557511722",
      "매물정보": "매물 보러가기"
    },
    {
      "매물ID": "2558395100",
      "URL": "https://fin.land.naver.com/articles/2558395100",
      "매물정보": "매물 보러가기"
    },
    {
      "매물ID": "2557688988",
      "URL": "https://fin.land.naver.com/articles/2557688988",
      "매물정보": "매물 보러가기"
    },
    {
      "매물ID": "2560784530",
      "URL": "https://fin.land.naver.com/articles/2560784530",
      "매물정보": "매물 보러가기"
    },
    {
      "매물ID": "2561881409",
      "URL": "https://fin.land.naver.com/articles/2561881409",
      "매물정보": "매물 보러가기"
    },
    {
      "매물ID": "2560400372",
      "URL": "https://fin.land.naver.com/articles/2560400372",
      "매물정보": "매물 보러가기"
    },
    {
      "매물ID": "2560310927",
      "URL": "https://fin.land.naver.com/articles/2560310927",
      "매물정보": "매물 보러가기"
    },
    {
      "매물ID": "2559839332",
      "URL": "https://fin.land.naver.com/articles/2559839332",
      "매물정보": "매물 보러가기"
    },
    {
      "매물ID": "2561888008",
      "URL": "https://fin.land.naver.com/articles/2561888008",
      "매물정보": "매물 보러가기"
    },
    {
      "매물ID": "2559360952",
      "URL": "https://fin.land.naver.com/articles/2559360952",
      "매물정보": "매물 보러가기"
    },
    {
      "매물ID": "2560242762",
      "URL": "https://fin.land.naver.com/articles/2560242762",
      "매물정보": "매물 보러가기"
    },
    {
      "매물ID": "2556352793",
      "URL": "https://fin.land.naver.com/articles/2556352793",
      "매물정보": "매물 보러가기"
    }
  ]
}